{
  "type": "FeatureCollection",
  "features": [
    {
      "type": "Feature",
      "properties": {},
      "geometry": {
        "type": "LineString",
        "coordinates": [
          [-118.506001, 34.022483],
          [-118.503432, 34.020312],
          [-118.498691, 34.024158],
          [-118.490471, 34.01714]
        ]
      }
    },
    {
      "type": "Feature",
      "properties": {},
      "geometry": {
        "type": "LineString",
        "coordinates": [
          [-118.502505, 34.019597],
          [-118.501833, 34.01896],
          [-118.497091, 34.022807],
          [-118.490471, 34.01714]
        ]
      }
    },
    {
      "type": "Feature",
      "properties": {},
      "geometry": {
        "coordinates": [-118.50596090533543, 34.022460191804115],
        "type": "Point"
      }
    },
    {
      "type": "Feature",
      "properties": {},
      "geometry": {
        "coordinates": [-118.50348840103229, 34.020366600906584],
        "type": "Point"
      }
    },
    {
      "type": "Feature",
      "properties": {},
      "geometry": {
        "coordinates": [-118.50251276419922, 34.019591183766934],
        "type": "Point"
      }
    },
    {
      "type": "Feature",
      "properties": {},
      "geometry": {
        "coordinates": [-118.50187124956977, 34.01899299998955],
        "type": "Point"
      }
    },
    {
      "type": "Feature",
      "properties": {},
      "geometry": {
        "coordinates": [-118.5002540981065, 34.020244750112056],
        "type": "Point"
      }
    },
    {
      "type": "Feature",
      "properties": {},
      "geometry": {
        "coordinates": [-118.4974207418241, 34.022548808269576],
        "type": "Point"
      }
    },
    {
      "type": "Feature",
      "properties": {},
      "geometry": {
        "coordinates": [-118.49587041480183, 34.021773411064444],
        "type": "Point"
      }
    },
    {
      "type": "Feature",
      "properties": {},
      "geometry": {
        "coordinates": [-118.49371866781372, 34.0199456610537],
        "type": "Point"
      }
    },
    {
      "type": "Feature",
      "properties": {},
      "geometry": {
        "coordinates": [-118.4905378244402, 34.01720950111492],
        "type": "Point"
      }
    }
  ]
}
